lazycats/__init__.py
lazycats/np.py
lazycats-0.1.0.dist-info/LICENSE
lazycats-0.1.0.dist-info/METADATA
lazycats-0.1.0.dist-info/WHEEL
lazycats-0.1.0.dist-info/top_level.txt
lazycats-0.1.0.dist-info/RECORD
