Metadata-Version: 2.1
Name: lazycats
Version: 0.1.0
Summary: Collection of utility functions
Home-page: https://github.com/cjbayron/lazycats
Author: Christopher John Bayron
Author-email: cjdbayron@gmail.com
License: UNKNOWN
Platform: UNKNOWN
Classifier: Programming Language :: Python :: 3
Classifier: License :: OSI Approved :: MIT License
Classifier: Operating System :: OS Independent
Requires-Python: >=3.6
Requires-Dist: numpy
